karabo/__init__.py
karabo/_version.py
karabo/version.py
karabo/config_db/__init__.py
karabo/config_db/configuration_database.py
karabo/config_db/models.py
karabo/config_db/utils.py
karabo/config_db/tests/__init__.py
karabo/config_db/tests/test_configuration_database.py
karabo/config_db/tests/test_utils.py
karabo/interactive/__init__.py
karabo/interactive/container_monitor.py
karabo/interactive/convert_config_db.py
karabo/interactive/convert_device_project.py
karabo/interactive/deviceClient.py
karabo/interactive/ideviceclient.py
karabo/interactive/ikarabo.py
karabo/interactive/karabo.py
karabo/interactive/scene2cpp.py
karabo/interactive/scene2python.py
karabo/interactive/startkarabo.py
karabo/interactive/webaggregatorserver.py
karabo/interactive/webserver.py
karabo/interactive/static/docs.html
karabo/interactive/static/favicon.ico
karabo/interactive/static/karabo.css
karabo/interactive/static/logger.js
karabo/interactive/templates/aggregator_index.html
karabo/interactive/templates/index.html
karabo/interactive/templates/index_row.html
karabo/interactive/templates/log.html
karabo/interactive/templates/log_row.html
karabo/interactive/templates/refresh.html
karabo/interactive/tests/__init__.py
karabo/interactive/tests/test_migrate_config_db.py
karabo/interactive/tests/test_scene2python.py
karabo/middlelayer/__init__.py
karabo/middlelayer/broker.py
karabo/middlelayer/configuration.py
karabo/middlelayer/conftest.py
karabo/middlelayer/device.py
karabo/middlelayer/device_client.py
karabo/middlelayer/device_interface.py
karabo/middlelayer/device_server.py
karabo/middlelayer/devicenode.py
karabo/middlelayer/eventloop.py
karabo/middlelayer/heartbeat_mixin.py
karabo/middlelayer/ikarabo.py
karabo/middlelayer/injectable.py
karabo/middlelayer/logger.py
karabo/middlelayer/macro.py
karabo/middlelayer/macro_server.py
karabo/middlelayer/metamacro.py
karabo/middlelayer/output.py
karabo/middlelayer/pipeline.py
karabo/middlelayer/proxy.py
karabo/middlelayer/signalslot.py
karabo_karathon-3.0.8.dist-info/licenses/LICENSE.md
karabo_karathon-3.0.8.dist-info/METADATA
karabo_karathon-3.0.8.dist-info/WHEEL
karabo_karathon-3.0.8.dist-info/entry_points.txt
karabo_karathon-3.0.8.dist-info/top_level.txt
karabo_karathon-3.0.8.dist-info/RECORD
