Metadata-Version: 2.4
Name: karabo.karathon
Version: 3.0.8
Summary: Karabo's Karathon Python API
Author-email: European XFEL GmbH <opensource@xfel.eu>
Maintainer-email: "S. Hauf" <steffen.hauf@xfel.eu>, "D. Goeries" <dennis.goeries@xfel.eu>
License-Expression: MPL-2.0
Project-URL: Homepage, https://github.com/European-XFEL/Karabo
Project-URL: Bug Reports, https://github.com/European-XFEL/Karabo/issues
Project-URL: Source, https://github.com/European-XFEL/Karabo
Keywords: Karabo,SCADA,async,control system
Classifier: Development Status :: 5 - Production/Stable
Classifier: Intended Audience :: Developers
Classifier: Intended Audience :: Science/Research
Requires-Python: >=3.12
License-File: LICENSE.md
Requires-Dist: SQLAlchemy==2.0.44
Requires-Dist: aiomysql==0.2.0
Requires-Dist: aiormq==3.3.1
Requires-Dist: aiosqlite==0.21.0
Requires-Dist: ipython==8.17.2
Requires-Dist: karabo-native==3.0.8
Requires-Dist: lxml==6.0.2
Requires-Dist: numpy==2.1.3
Requires-Dist: pint>=0.24.4
Requires-Dist: psutil==5.9.5
Requires-Dist: pyexistdb==1.0.1
Requires-Dist: pytest==8.3.3
Requires-Dist: pytest_asyncio==1.2.0
Requires-Dist: python_dateutil==2.9.0.post0
Requires-Dist: pytz==2020.5
Requires-Dist: sqlmodel==0.0.22
Requires-Dist: tornado==6.3.3
Requires-Dist: traits==6.4.3
Requires-Dist: tzlocal==5.0.1
Requires-Dist: urllib3==1.26.20
Dynamic: license-file
